LICENSE.txt
README.md
setup.cfg
setup.py
yhmgit/__init__.py
yhmgit/yhmgit.py
yhmgit.egg-info/PKG-INFO
yhmgit.egg-info/SOURCES.txt
yhmgit.egg-info/dependency_links.txt
yhmgit.egg-info/requires.txt
yhmgit.egg-info/top_level.txt