Metadata-Version: 2.1
Name: yhmgit
Version: 0.1
Summary: yh branch git manager util
Home-page: http://gitlab.yonghui.cn/operation-xm-qdjg/yhgit.git
Download-URL: https://github.com/yonghuifan21/yhci-util/blob/master/dist/yhciutil-0.1.tar.gz
Author: yonghuifan21
Author-email: jackfan1@yonghui.com
License: MIT
Keywords: yhciutil,yhci,ciutil
Platform: UNKNOWN
Classifier: Development Status :: 3 - Alpha
Classifier: Intended Audience :: Developers
Classifier: Topic :: Software Development :: Build Tools
Classifier: License :: OSI Approved :: MIT License
Classifier: Programming Language :: Python :: 3
Classifier: Programming Language :: Python :: 3.4
Classifier: Programming Language :: Python :: 3.5
Classifier: Programming Language :: Python :: 3.6
License-File: LICENSE.txt
